[{"h1":"تحاول دون نتيجة.. إليك خدعة النوم السحرية"},{"image":"https://images.skynewsarabia.com/images/v4/2022/10/31/1567461/700/394/1-1567461.jpg"},{"caption":"دراسة أكدت أن توقيت نومك يؤثر على صحتك"},{"mainParagraphe":"تعاني نسبة كبيرة من الناس للدخول بالنوم سريعا، إلا أن المحاولات غالبا ما تفشل ويدخل الشخص في دورة أرق طويلة لا يعرف التخلص منها."},{"p":"أحد الأطباء الجراحين يدعى كاران راجان كشف على حسابه في تيك توك عن خدعة غريبة من الممكن أن تساعد حقا على النوم سريعا."},{"p":"تقوم خدعة راجان على المفعول العكسي أو ما يعرف في علم النفس بـ\"النية المتناقضة\"."},{"p":"وقال راجان: \"غالبا ما تبدأ رحلة النوم مصرا على تحقيق الهدف، تستلقي في السرير، وعيناك مفتوحتان، تجاهد كي تنام دون نتيجة\"."},{"p":"وأضاف: \"على العكس من ذلك، قل لنفسك، لا تذهب للنوم، لا تنام، في كثير من الحالات، ستشعر بالتعب وستنام، وقد نجح ذلك معي\"."},{"p":"في المتوسط ، يحتاج البالغون ما بين سبع إلى تسع ساعات من النوم كل ليلة."},{"p":"علامات وجود الأرق:"},{"li":"تجد صعوبة في النوم."},{"li":"الاستيقاظ عدة مرات خلال الليل."},{"li":"الشعور بالتعب بعد الاستيقاظ."},{"li":"تجد صعوبة في الحصول على قيلولة أثناء النهار حتى وإن كنت متعبا."},{"li":"تشعر بالتعب وسرعة الانفعال أثناء النهار."},{"p":""}]