[{"image":"https://images.skynewsarabia.com/images/v1/2023/07/11/1636083/1600/640/1-1636083.jpg"},{"h1":"بركان أيسلندا الثائر"},{"h2":"ثار الإثنين بركان يبعد حوالي 30 كيلومترا من العاصمة الإيسلندية ريكيافيك، وفق ما أعلنت مصلحة الأرصاد الجوية في البلاد."},{"image":"https://images.skynewsarabia.com/images/v1/2023/07/11/1636080/900/506/1-1636080.jpg"},{"h3":"هذه هي المرة الثالثة خلال سنتين التي تتدفّق فيها الحمم البركانية في المنطقة."},{"image":"https://images.skynewsarabia.com/images/v1/2023/07/11/1636081/900/506/1-1636081.jpg"},{"h3":"الثوران يحدث في منطقة تقع إلى الشمال من جبل ليتلي هروتور."},{"image":"https://images.skynewsarabia.com/images/v1/2023/07/11/1636082/900/506/1-1636082.jpg"},{"h3":"أظهرت لقطات تشكّل سحابة كبيرة ترتفع من الأرض وتدفّقا كثيفا للحمم البركانية."},{"image":"https://images.skynewsarabia.com/images/v1/2023/07/11/1636084/900/506/1-1636084.jpg"},{"h3":"تم تسجيل آلاف الهزات الأرضية في المنطقة قبل نحو أسبوع من الثوران، في مؤشر دلّ على تحرّك الصهارة تحت الأرض وعلى أن الثوران بات وشيكا."},{"image":"https://images.skynewsarabia.com/images/v1/2023/07/11/1636085/900/506/1-1636085.jpg"},{"h3":"نصحت السلطات الإيسلندية بعدم التوجه إلى الموقع بانتظار إجراء تقييم للأوضاع."},{"image":"https://images.skynewsarabia.com/images/v1/2023/07/11/1636086/900/506/1-1636086.jpg"},{"h3":"لم تتأثر حركة الطيران في مطار كيفلافيك بثوران البركان."},{"image":"https://images.skynewsarabia.com/images/v1/2023/07/11/1636087/900/506/1-1636087.jpg"},{"h3":"البركان يبعد حوالي 30 كيلومترا من العاصمة الإيسلندية ريكيافيك."}]