[{"h1":"صدمة في ليفربول وكلوب في موقف محرج.. نجم الوسط يرفض التوقيع"},{"image":"https://images.skynewsarabia.com/images/v1/2023/05/02/1617403/700/394/1-1617403.jpg"},{"caption":"الألماني يورغن كلوب مدرب ليفربول"},{"mainParagraphe":"في يوم \"جنوني\" بعالم الانتقالات الأوروبية، بعد أن تبين أن نادي ليفربول \"خطف\" صفقة غريمه تشلسي، ونجح بالتوقيع مع لاعب وسط برايتون مويزيس كايسيدو، اكتشف \"الريدز\" أن اللاعب يرفض الانتقال."},{"p":"يوم الجمعة، نشرت وسائل الإعلام العالمية خبر تحطيم ليفربول الرقم القياسي للبريميرليغ، وتسجيل أعلى صفقة انتقال بتاريخ الدوري، بالتوقيع مع نجم منتخب الإكوادور ونادي برايتون الإنجليزي، مويزيس كايسيدو، مقابل 110 مليون جنيه أسترليني (140 مليون دولار)."},{"p":"صفقة ليفربول جاءت مفاجئة للكثيرين، ووصفتها الصحف البريطانية بـ\"عملية الخطف\"، بعد أن كان تشلسي يفاوض كايسيدو على مدار أسابيع."},{"p":"حتى أن المدرب يورغن كلوب، خرج في المؤتمر الصحفي وقال إنه نجح بالتعاقد مع كايسيدو."},{"h2":"مفاجأة غير سارة"},{"p":"لكن بعدها بساعة، فجر خبير الانتقالات العالمي فابريتسيو رومانو \"قنبلة\"، وأكد أن كايسيدو لا يرغب في الانتقال إلى ليفربول، وأنه أخبر \"الريدز\" برفضه التوقيع."},{"p":"أشار رومانو إلى أن كايسيدو أراد الالتزام بكلمته التي أعطاها لإدارة تشلسي في مايو، وأنه لن ينتقل سوى إلى النادي اللندني."},{"p":"الأخبار وضعت ليفربول في مأزق، خاصة بعد الإعلان عن الصفقة من قبل كلوب، لتمثل حالة \"جنونية\" في عالم الانتقالات."},{"p":"حتى الآن، لا يزال القرار النهائي \"معلقا\"، ولكن ليفربول يبدو في طريقه لخسارة توقيع النجم الإكوادوري بطريقة \"محرجة\"."}]